README.rst
setup.py
django_qiniu/__init__.py
django_qiniu/backends.py
django_qiniu/utils.py
django_qiniu.egg-info/PKG-INFO
django_qiniu.egg-info/SOURCES.txt
django_qiniu.egg-info/dependency_links.txt
django_qiniu.egg-info/requires.txt
django_qiniu.egg-info/top_level.txt
django_qiniu/templatetags/__init__.py
django_qiniu/templatetags/qiniu_helper.py