Metadata-Version: 1.1
Name: django-qiniu
Version: 0.1.4
Summary: qiniu file(image) upload helper utils
Home-page: https://github.com/9nix00/django-qiniu
Author: wangwenpei
Author-email: wangwenpei@nextoa.com
License: http://opensource.org/licenses/MIT
Download-URL: https://github.com/9nix00/django-qiniu/archive/master.zip
Keywords: django_qiniu,
Platform: UNKNOWN
